gsc_bulk_indexer/__init__.py
gsc_bulk_indexer/auth.py
gsc_bulk_indexer/gsc.py
gsc_bulk_indexer/indexer.py
gsc_bulk_indexer/parse.py
gsc_bulk_indexer/submit.py
gsc_bulk_indexer/utils.py
gsc_bulk_indexer-0.1.2.dist-info/LICENSE
gsc_bulk_indexer-0.1.2.dist-info/METADATA
gsc_bulk_indexer-0.1.2.dist-info/WHEEL
gsc_bulk_indexer-0.1.2.dist-info/entry_points.txt
gsc_bulk_indexer-0.1.2.dist-info/RECORD
