Metadata-Version: 2.1
Name: gsc-bulk-indexer
Version: 0.1.2
Summary: Utilities for automatically submitting website pages for indexing in bulk to Google Search Console
Home-page: https://github.com/konigle/google-bulk-indexer
License: MIT
Keywords: google search console,bulk indexing,seo,search engine optimization
Author: Konigle Developers
Author-email: developers@konigle.com
Maintainer: Konigle Developers
Maintainer-email: developers@konigle.com
Requires-Python: >=3.9,<4.0
Classifier: License :: OSI Approved :: MIT License
Classifier: Programming Language :: Python :: 3
Classifier: Programming Language :: Python :: 3.9
Classifier: Programming Language :: Python :: 3.10
Classifier: Programming Language :: Python :: 3.11
Classifier: Programming Language :: Python :: 3.12
Requires-Dist: aiohttp (>=3.9.5,<4.0.0)
Requires-Dist: google-auth (>=2.27.0,<3.0.0)
Requires-Dist: python-dateutil (>=2.8.2,<3.0.0)
Requires-Dist: requests (>=2.31.0,<3.0.0)
Project-URL: Repository, https://github.com/konigle/google-bulk-indexer
